urw/__init__.py
urw/urw.py
urw/wordlist.txt
urw-0.0.7.dist-info/METADATA
urw-0.0.7.dist-info/WHEEL
urw-0.0.7.dist-info/top_level.txt
urw-0.0.7.dist-info/RECORD
