Metadata-Version: 2.1
Name: urw
Version: 0.0.7
Summary: Urdu word/phrase generator.
Author: siphr
Author-email: pypi@techtum.dev
License: UNKNOWN
Project-URL: Homepage, https://www.techtum.dev/work-urw-220310.html
Project-URL: Source, https://github.com/siphr/urw
Project-URL: Tracker, https://github.com/siphr/urw/issues
Keywords: urdu,random,words,generator
Platform: any
